{
  "name": "show-table",
  "title": "Show Table",
  "description": "Adds a 'Show Players' option to the header menu for rollable tables",
  "author": "CRASH1115#2944",
  "authors": [],
  "url": "https://github.com/crash1115/show-table",
  "readme": "https://github.com/crash1115/show-table/blob/main/README.md",
  "bugs": "https://github.com/crash1115/show-table/issues",
  "flags": {},
  "version": "1.0.0",
  "minimumCoreVersion": "0.8.9",
  "compatibleCoreVersion": "9",
  "scripts": [],
  "esmodules": ["show-table.js"],
  "styles": [ "styles/show-table.css" ],
  "languages": [],
  "packs": [],
  "system": [],
  "dependencies": [ {"name": "lib-wrapper"} ],
  "socket": true,
  "manifest": "https://raw.githubusercontent.com/crash1115/show-table/main/module.json",
  "download": "https://github.com/crash1115/show-table/releases/download/v1.0.0/show-table.zip",
  "protected": false,
  "coreTranslation": false
}
